taskman_sv/__init__.py
taskman_sv/cli.py
taskman_sv/interface.py
taskman_sv/taskman_backend.py
taskman_sv-0.8.0.dist-info/METADATA
taskman_sv-0.8.0.dist-info/WHEEL
taskman_sv-0.8.0.dist-info/entry_points.txt
taskman_sv-0.8.0.dist-info/top_level.txt
taskman_sv-0.8.0.dist-info/RECORD
