Metadata-Version: 2.4
Name: taskman-sv
Version: 0.8.0
Summary: A secure task management and note-taking application
Author-email: Shreedhar <shreedharv16@gmail.com>
Project-URL: Homepage, https://github.com/shreedharv16/taskman
Project-URL: Repository, https://github.com/shreedharv16/taskman.git
Keywords: task,management,notes,productivity
Classifier: Development Status :: 3 - Alpha
Classifier: Intended Audience :: End Users/Desktop
Classifier: License :: OSI Approved :: MIT License
Classifier: Programming Language :: Python :: 3
Classifier: Programming Language :: Python :: 3.8
Classifier: Programming Language :: Python :: 3.9
Classifier: Programming Language :: Python :: 3.10
Classifier: Operating System :: OS Independent
Requires-Python: >=3.8
Requires-Dist: colorama
Requires-Dist: cryptography
Requires-Dist: bcrypt
Requires-Dist: setuptools
Requires-Dist: tqdm
Requires-Dist: requests
Requires-Dist: plyer
Requires-Dist: pywin32; platform_system == "Windows"
